[
  {
    "ContainingType": "XuongMayNhom8.API.Controllers.AuthController",
    "Method": "Login",
    "RelativePath": "api/auth/login",
    "HttpMethod": "POST",
    "IsController": true,
    "Order": 0,
    "Parameters": [
      {
        "Name": "userLogin",
        "Type": "XuongMayNhom8.Repositories.Configuration.UserLogin",
        "IsRequired": true
      }
    ],
    "ReturnTypes": []
  },
  {
    "ContainingType": "XuongMayNhom8.API.Controllers.CategoryController",
    "Method": "GetAll",
    "RelativePath": "api/Category/categories",
    "HttpMethod": "GET",
    "IsController": true,
    "Order": 0,
    "Parameters": [],
    "ReturnTypes": [
      {
        "Type": "System.Collections.Generic.IEnumerable\u00601[[XuongMayNhom8.Repositories.Models.Danhmuc, XuongMayNhom8.Repositories, Version=1.0.0.0, Culture=neutral, PublicKeyToken=null]]",
        "MediaTypes": [
          "text/plain",
          "application/json",
          "text/json"
        ],
        "StatusCode": 200
      }
    ]
  },
  {
    "ContainingType": "XuongMayNhom8.API.Controllers.CategoryController",
    "Method": "Create",
    "RelativePath": "api/Category/categories",
    "HttpMethod": "POST",
    "IsController": true,
    "Order": 0,
    "Parameters": [
      {
        "Name": "value",
        "Type": "XuongMayNhom8.Repositories.Models.Danhmuc",
        "IsRequired": true
      }
    ],
    "ReturnTypes": [
      {
        "Type": "XuongMayNhom8.Repositories.Models.Danhmuc",
        "MediaTypes": [
          "text/plain",
          "application/json",
          "text/json"
        ],
        "StatusCode": 200
      }
    ]
  },
  {
    "ContainingType": "XuongMayNhom8.API.Controllers.CategoryController",
    "Method": "GetById",
    "RelativePath": "api/Category/categories/{id}",
    "HttpMethod": "GET",
    "IsController": true,
    "Order": 0,
    "Parameters": [
      {
        "Name": "id",
        "Type": "System.Int32",
        "IsRequired": true
      }
    ],
    "ReturnTypes": [
      {
        "Type": "XuongMayNhom8.Repositories.Models.Danhmuc",
        "MediaTypes": [
          "text/plain",
          "application/json",
          "text/json"
        ],
        "StatusCode": 200
      }
    ]
  },
  {
    "ContainingType": "XuongMayNhom8.API.Controllers.CategoryController",
    "Method": "Update",
    "RelativePath": "api/Category/categories/{id}",
    "HttpMethod": "PUT",
    "IsController": true,
    "Order": 0,
    "Parameters": [
      {
        "Name": "id",
        "Type": "System.Int32",
        "IsRequired": true
      },
      {
        "Name": "value",
        "Type": "XuongMayNhom8.Repositories.Models.Danhmuc",
        "IsRequired": true
      }
    ],
    "ReturnTypes": [
      {
        "Type": "XuongMayNhom8.Repositories.Models.Danhmuc",
        "MediaTypes": [
          "text/plain",
          "application/json",
          "text/json"
        ],
        "StatusCode": 200
      }
    ]
  },
  {
    "ContainingType": "XuongMayNhom8.API.Controllers.CategoryController",
    "Method": "Delete",
    "RelativePath": "api/Category/categories/{id}",
    "HttpMethod": "DELETE",
    "IsController": true,
    "Order": 0,
    "Parameters": [
      {
        "Name": "id",
        "Type": "System.Int32",
        "IsRequired": true
      }
    ],
    "ReturnTypes": []
  },
  {
    "ContainingType": "XuongMayNhom8.API.Controllers.OrderController",
    "Method": "GetAllOrder",
    "RelativePath": "api/Order",
    "HttpMethod": "GET",
    "IsController": true,
    "Order": 0,
    "Parameters": [
      {
        "Name": "pageNumber",
        "Type": "System.Int32",
        "IsRequired": false
      },
      {
        "Name": "pageSize",
        "Type": "System.Int32",
        "IsRequired": false
      }
    ],
    "ReturnTypes": []
  },
  {
    "ContainingType": "XuongMayNhom8.API.Controllers.OrderController",
    "Method": "CreateOrder",
    "RelativePath": "api/Order",
    "HttpMethod": "POST",
    "IsController": true,
    "Order": 0,
    "Parameters": [
      {
        "Name": "donhang",
        "Type": "XuongMayNhom8.Repositories.Models.Donhang",
        "IsRequired": true
      }
    ],
    "ReturnTypes": []
  },
  {
    "ContainingType": "XuongMayNhom8.API.Controllers.OrderController",
    "Method": "UpdateOrder",
    "RelativePath": "api/Order",
    "HttpMethod": "PUT",
    "IsController": true,
    "Order": 0,
    "Parameters": [
      {
        "Name": "donhang",
        "Type": "XuongMayNhom8.Repositories.Models.Donhang",
        "IsRequired": true
      }
    ],
    "ReturnTypes": []
  },
  {
    "ContainingType": "XuongMayNhom8.API.Controllers.OrderController",
    "Method": "GetSpecificOrder",
    "RelativePath": "api/Order/{orderId}",
    "HttpMethod": "GET",
    "IsController": true,
    "Order": 0,
    "Parameters": [
      {
        "Name": "orderId",
        "Type": "System.Int32",
        "IsRequired": true
      }
    ],
    "ReturnTypes": []
  },
  {
    "ContainingType": "XuongMayNhom8.API.Controllers.OrderController",
    "Method": "DeleteOrder",
    "RelativePath": "api/Order/{orderId}",
    "HttpMethod": "DELETE",
    "IsController": true,
    "Order": 0,
    "Parameters": [
      {
        "Name": "orderId",
        "Type": "System.Int32",
        "IsRequired": true
      }
    ],
    "ReturnTypes": []
  },
  {
    "ContainingType": "XuongMayNhom8.API.Controllers.ProductController",
    "Method": "GetAll",
    "RelativePath": "api/Product/products",
    "HttpMethod": "GET",
    "IsController": true,
    "Order": 0,
    "Parameters": [],
    "ReturnTypes": [
      {
        "Type": "System.Collections.Generic.IEnumerable\u00601[[XuongMayNhom8.Repositories.Models.Sanpham, XuongMayNhom8.Repositories, Version=1.0.0.0, Culture=neutral, PublicKeyToken=null]]",
        "MediaTypes": [
          "text/plain",
          "application/json",
          "text/json"
        ],
        "StatusCode": 200
      }
    ]
  },
  {
    "ContainingType": "XuongMayNhom8.API.Controllers.ProductController",
    "Method": "Create",
    "RelativePath": "api/Product/products",
    "HttpMethod": "POST",
    "IsController": true,
    "Order": 0,
    "Parameters": [
      {
        "Name": "value",
        "Type": "XuongMayNhom8.Repositories.Models.Sanpham",
        "IsRequired": true
      }
    ],
    "ReturnTypes": [
      {
        "Type": "XuongMayNhom8.Repositories.Models.Sanpham",
        "MediaTypes": [
          "text/plain",
          "application/json",
          "text/json"
        ],
        "StatusCode": 200
      }
    ]
  },
  {
    "ContainingType": "XuongMayNhom8.API.Controllers.ProductController",
    "Method": "GetProduct",
    "RelativePath": "api/Product/products/{id}",
    "HttpMethod": "GET",
    "IsController": true,
    "Order": 0,
    "Parameters": [
      {
        "Name": "id",
        "Type": "System.Int32",
        "IsRequired": true
      }
    ],
    "ReturnTypes": [
      {
        "Type": "XuongMayNhom8.Repositories.Models.Sanpham",
        "MediaTypes": [
          "text/plain",
          "application/json",
          "text/json"
        ],
        "StatusCode": 200
      }
    ]
  },
  {
    "ContainingType": "XuongMayNhom8.API.Controllers.ProductController",
    "Method": "Update",
    "RelativePath": "api/Product/products/{id}",
    "HttpMethod": "PUT",
    "IsController": true,
    "Order": 0,
    "Parameters": [
      {
        "Name": "id",
        "Type": "System.Int32",
        "IsRequired": true
      },
      {
        "Name": "value",
        "Type": "XuongMayNhom8.Repositories.Models.Sanpham",
        "IsRequired": true
      }
    ],
    "ReturnTypes": [
      {
        "Type": "XuongMayNhom8.Repositories.Models.Sanpham",
        "MediaTypes": [
          "text/plain",
          "application/json",
          "text/json"
        ],
        "StatusCode": 200
      }
    ]
  },
  {
    "ContainingType": "XuongMayNhom8.API.Controllers.ProductController",
    "Method": "Delete",
    "RelativePath": "api/Product/products/{id}",
    "HttpMethod": "DELETE",
    "IsController": true,
    "Order": 0,
    "Parameters": [
      {
        "Name": "id",
        "Type": "System.Int32",
        "IsRequired": true
      }
    ],
    "ReturnTypes": []
  },
  {
    "ContainingType": "XuongMayNhom8.API.Controllers.ProductionLineController",
    "Method": "GetAll",
    "RelativePath": "api/ProductionLine",
    "HttpMethod": "GET",
    "IsController": true,
    "Order": 0,
    "Parameters": [],
    "ReturnTypes": []
  },
  {
    "ContainingType": "XuongMayNhom8.API.Controllers.ProductionLineController",
    "Method": "Add",
    "RelativePath": "api/ProductionLine",
    "HttpMethod": "POST",
    "IsController": true,
    "Order": 0,
    "Parameters": [
      {
        "Name": "chuyen",
        "Type": "XuongMayNhom8.Repositories.Models.Chuyen",
        "IsRequired": true
      }
    ],
    "ReturnTypes": []
  },
  {
    "ContainingType": "XuongMayNhom8.API.Controllers.ProductionLineController",
    "Method": "GetById",
    "RelativePath": "api/ProductionLine/{id}",
    "HttpMethod": "GET",
    "IsController": true,
    "Order": 0,
    "Parameters": [
      {
        "Name": "id",
        "Type": "System.Int32",
        "IsRequired": true
      }
    ],
    "ReturnTypes": []
  },
  {
    "ContainingType": "XuongMayNhom8.API.Controllers.ProductionLineController",
    "Method": "Delete",
    "RelativePath": "api/ProductionLine/{id}",
    "HttpMethod": "DELETE",
    "IsController": true,
    "Order": 0,
    "Parameters": [
      {
        "Name": "id",
        "Type": "System.Int32",
        "IsRequired": true
      }
    ],
    "ReturnTypes": []
  },
  {
    "ContainingType": "XuongMayNhom8.API.Controllers.ProductionLineController",
    "Method": "Update",
    "RelativePath": "api/ProductionLine/{id}",
    "HttpMethod": "PUT",
    "IsController": true,
    "Order": 0,
    "Parameters": [
      {
        "Name": "id",
        "Type": "System.Int32",
        "IsRequired": true
      },
      {
        "Name": "chuyen",
        "Type": "XuongMayNhom8.Repositories.Models.Chuyen",
        "IsRequired": true
      }
    ],
    "ReturnTypes": []
  },
  {
    "ContainingType": "XuongMayNhom8.API.Controllers.ProductionLineController",
    "Method": "GetAll",
    "RelativePath": "api/ProductionLine/page/{pageNumber}/{pageSize}",
    "HttpMethod": "GET",
    "IsController": true,
    "Order": 0,
    "Parameters": [
      {
        "Name": "pageNumber",
        "Type": "System.Int32",
        "IsRequired": true
      },
      {
        "Name": "pageSize",
        "Type": "System.Int32",
        "IsRequired": true
      }
    ],
    "ReturnTypes": []
  },
  {
    "ContainingType": "XuongMayNhom8.API.Controllers.TaskController",
    "Method": "GetAll",
    "RelativePath": "api/Task",
    "HttpMethod": "GET",
    "IsController": true,
    "Order": 0,
    "Parameters": [],
    "ReturnTypes": []
  },
  {
    "ContainingType": "XuongMayNhom8.API.Controllers.TaskController",
    "Method": "Add",
    "RelativePath": "api/Task",
    "HttpMethod": "POST",
    "IsController": true,
    "Order": 0,
    "Parameters": [
      {
        "Name": "task",
        "Type": "XuongMayNhom8.Repositories.Models.Congviec",
        "IsRequired": true
      }
    ],
    "ReturnTypes": []
  },
  {
    "ContainingType": "XuongMayNhom8.API.Controllers.TaskController",
    "Method": "GetById",
    "RelativePath": "api/Task/{id}",
    "HttpMethod": "GET",
    "IsController": true,
    "Order": 0,
    "Parameters": [
      {
        "Name": "id",
        "Type": "System.Int32",
        "IsRequired": true
      }
    ],
    "ReturnTypes": []
  },
  {
    "ContainingType": "XuongMayNhom8.API.Controllers.TaskController",
    "Method": "Delete",
    "RelativePath": "api/Task/{id}",
    "HttpMethod": "DELETE",
    "IsController": true,
    "Order": 0,
    "Parameters": [
      {
        "Name": "id",
        "Type": "System.Int32",
        "IsRequired": true
      }
    ],
    "ReturnTypes": []
  },
  {
    "ContainingType": "XuongMayNhom8.API.Controllers.TaskController",
    "Method": "Update",
    "RelativePath": "api/Task/{id}",
    "HttpMethod": "PUT",
    "IsController": true,
    "Order": 0,
    "Parameters": [
      {
        "Name": "id",
        "Type": "System.Int32",
        "IsRequired": true
      },
      {
        "Name": "task",
        "Type": "XuongMayNhom8.Repositories.Models.Congviec",
        "IsRequired": true
      }
    ],
    "ReturnTypes": []
  },
  {
    "ContainingType": "XuongMayNhom8.API.Controllers.TaskController",
    "Method": "GetAll",
    "RelativePath": "api/Task/page/{pageNumber}/{pageSize}",
    "HttpMethod": "GET",
    "IsController": true,
    "Order": 0,
    "Parameters": [
      {
        "Name": "pageNumber",
        "Type": "System.Int32",
        "IsRequired": true
      },
      {
        "Name": "pageSize",
        "Type": "System.Int32",
        "IsRequired": true
      }
    ],
    "ReturnTypes": []
  },
  {
    "ContainingType": "XuongMayNhom8.API.Controllers.UserController",
    "Method": "GetUsers",
    "RelativePath": "api/user",
    "HttpMethod": "GET",
    "IsController": true,
    "Order": 0,
    "Parameters": [],
    "ReturnTypes": []
  },
  {
    "ContainingType": "XuongMayNhom8.API.Controllers.UserController",
    "Method": "CreateUser",
    "RelativePath": "api/user",
    "HttpMethod": "POST",
    "IsController": true,
    "Order": 0,
    "Parameters": [
      {
        "Name": "user",
        "Type": "XuongMayNhom8.Repositories.Models.User",
        "IsRequired": true
      }
    ],
    "ReturnTypes": []
  },
  {
    "ContainingType": "XuongMayNhom8.API.Controllers.UserController",
    "Method": "GetUserById",
    "RelativePath": "api/user/{id}",
    "HttpMethod": "GET",
    "IsController": true,
    "Order": 0,
    "Parameters": [
      {
        "Name": "id",
        "Type": "System.Guid",
        "IsRequired": true
      }
    ],
    "ReturnTypes": []
  },
  {
    "ContainingType": "XuongMayNhom8.API.Controllers.UserController",
    "Method": "UpdateUser",
    "RelativePath": "api/user/{id}",
    "HttpMethod": "PUT",
    "IsController": true,
    "Order": 0,
    "Parameters": [
      {
        "Name": "id",
        "Type": "System.Guid",
        "IsRequired": true
      },
      {
        "Name": "user",
        "Type": "XuongMayNhom8.Repositories.Models.User",
        "IsRequired": true
      }
    ],
    "ReturnTypes": []
  },
  {
    "ContainingType": "XuongMayNhom8.API.Controllers.UserController",
    "Method": "DeleteUser",
    "RelativePath": "api/user/{id}",
    "HttpMethod": "DELETE",
    "IsController": true,
    "Order": 0,
    "Parameters": [
      {
        "Name": "id",
        "Type": "System.Guid",
        "IsRequired": true
      }
    ],
    "ReturnTypes": []
  }
]